gitbars
